{"query": "\u524d\u5e74\u5230\u53bb\u5e74\u4e4b\u95f4\uff0c\u5f20\u71a0\u7ecf\u5e38\u5750\u706b\u8f66\u53bb\u54ea\u4e9b\u5730\u65b9\uff1f", "nodes": [{"node_id": 0, "type": "PERSON", "property": {"FIRSTNAME": {"type": "string", "value": "\u5f20"}, "LASTNAME": {"type": "string", "value": "\u71a0"}}}, {"node_id": 1, "type": "ADDR", "property": {"location": {"name": "unknown", "granularity": null, "attribution": "\u76ee\u7684\u5730"}}}], "links": [{"link_id": 0, "source": 0, "target": 1, "key": "ARRIVED_AT", "property": {"time": {"time_start": "2018-01-01-00-00", "time_end": "2019-01-01-00-00", "granularity": "\u5e74", "fuzzy": null}}}], "targets": {"target_type": "node", "node_id": 1, "limit": "often"}}